jenkinsapi/.gitignore
jenkinsapi/__init__.py
jenkinsapi/api.py
jenkinsapi/artifact.py
jenkinsapi/build.py
jenkinsapi/config.py
jenkinsapi/constants.py
jenkinsapi/credential.py
jenkinsapi/credentials.py
jenkinsapi/custom_exceptions.py
jenkinsapi/executor.py
jenkinsapi/executors.py
jenkinsapi/fingerprint.py
jenkinsapi/jenkins.py
jenkinsapi/jenkinsbase.py
jenkinsapi/job.py
jenkinsapi/jobs.py
jenkinsapi/label.py
jenkinsapi/mutable_jenkins_thing.py
jenkinsapi/node.py
jenkinsapi/nodes.py
jenkinsapi/plugin.py
jenkinsapi/plugins.py
jenkinsapi/queue.py
jenkinsapi/result.py
jenkinsapi/result_set.py
jenkinsapi/view.py
jenkinsapi/views.py
jenkinsapi/command_line/__init__.py
jenkinsapi/command_line/jenkins_invoke.py
jenkinsapi/command_line/jenkinsapi_version.py
jenkinsapi/utils/__init__.py
jenkinsapi/utils/crumb_requester.py
jenkinsapi/utils/jenkins_launcher.py
jenkinsapi/utils/jsonp_to_json.py
jenkinsapi/utils/krb_requester.py
jenkinsapi/utils/manifest.py
jenkinsapi/utils/requester.py
jenkinsapi/utils/simple_post_logger.py
jenkinsapi-0.3.16.dist-info/METADATA
jenkinsapi-0.3.16.dist-info/WHEEL
jenkinsapi-0.3.16.dist-info/entry_points.txt
jenkinsapi-0.3.16.dist-info/licenses/LICENSE
jenkinsapi-0.3.16.dist-info/RECORD
