Metadata-Version: 2.4
Name: jenkinsapi
Version: 0.3.16
Summary: A Python API for accessing resources on a Jenkins continuous-integration server.
Author-email: Salim Fadhley <salimfadhley@gmail.com>, Aleksey Maksimov <ctpeko3a@gmail.com>, Clinton Steiner <clintonsteiner@gmail.com>
Maintainer-email: Aleksey Maksimov <ctpeko3a@gmail.com>, Clinton Steiner <clintonsteiner@gmail.com>
License: MIT license
License-File: LICENSE
Classifier: Development Status :: 5 - Production/Stable
Classifier: Environment :: Console
Classifier: Intended Audience :: Developers
Classifier: Intended Audience :: Information Technology
Classifier: Intended Audience :: System Administrators
Classifier: License :: OSI Approved :: MIT License
Classifier: Natural Language :: English
Classifier: Operating System :: OS Independent
Classifier: Programming Language :: Python
Classifier: Programming Language :: Python :: 3
Classifier: Programming Language :: Python :: 3.9
Classifier: Programming Language :: Python :: 3.10
Classifier: Programming Language :: Python :: 3.11
Classifier: Programming Language :: Python :: 3.12
Classifier: Programming Language :: Python :: 3.13
Classifier: Topic :: Software Development :: Testing
Classifier: Topic :: Utilities
Requires-Python: >=3.9
Requires-Dist: pytz>=2014.4
Requires-Dist: requests>=2.3.0
